agb/__init__.py
agb/_release.py
agb/agb.py
agb/config.py
agb/context.py
agb/context_manager.py
agb/context_sync.py
agb/exceptions.py
agb/extension.py
agb/logger.py
agb/session.py
agb/session_params.py
agb/version_utils.py
agb/api/__init__.py
agb/api/base_service.py
agb/api/client.py
agb/api/http_client.py
agb/api/models/__init__.py
agb/api/models/call_mcp_tool_request.py
agb/api/models/call_mcp_tool_response.py
agb/api/models/clear_context_request.py
agb/api/models/clear_context_response.py
agb/api/models/create_session_request.py
agb/api/models/create_session_response.py
agb/api/models/delete_context_file_request.py
agb/api/models/delete_context_file_response.py
agb/api/models/delete_context_request.py
agb/api/models/delete_context_response.py
agb/api/models/delete_session_async_request.py
agb/api/models/delete_session_async_response.py
agb/api/models/describe_context_files_request.py
agb/api/models/describe_context_files_response.py
agb/api/models/get_and_load_internal_context_request.py
agb/api/models/get_and_load_internal_context_response.py
agb/api/models/get_context_file_download_url_request.py
agb/api/models/get_context_file_download_url_response.py
agb/api/models/get_context_file_upload_url_request.py
agb/api/models/get_context_file_upload_url_response.py
agb/api/models/get_context_info_request.py
agb/api/models/get_context_info_response.py
agb/api/models/get_context_request.py
agb/api/models/get_context_response.py
agb/api/models/get_label_request.py
agb/api/models/get_label_response.py
agb/api/models/get_link_request.py
agb/api/models/get_link_response.py
agb/api/models/get_mcp_resource_request.py
agb/api/models/get_mcp_resource_response.py
agb/api/models/get_session_detail_request.py
agb/api/models/get_session_detail_response.py
agb/api/models/get_session_request.py
agb/api/models/get_session_response.py
agb/api/models/init_browser_request.py
agb/api/models/init_browser_response.py
agb/api/models/list_contexts_request.py
agbcloud_sdk-0.9.0.dist-info/licenses/LICENSE
agbcloud_sdk-0.9.0.dist-info/METADATA
agbcloud_sdk-0.9.0.dist-info/WHEEL
agbcloud_sdk-0.9.0.dist-info/top_level.txt
agbcloud_sdk-0.9.0.dist-info/RECORD
