Metadata-Version: 2.4
Name: agbcloud-sdk
Version: 0.9.0
Summary: AGB Python SDK
Author: AGB Team
License-Expression: Apache-2.0
Classifier: Development Status :: 3 - Alpha
Classifier: Intended Audience :: Developers
Classifier: Programming Language :: Python :: 3
Classifier: Programming Language :: Python :: 3.10
Classifier: Programming Language :: Python :: 3.11
Classifier: Programming Language :: Python :: 3.12
Requires-Python: >=3.10
License-File: LICENSE
Requires-Dist: requests>=2.25.0
Requires-Dist: python-dotenv>=0.19.0
Requires-Dist: cryptography>=44.0.0
Requires-Dist: httpx[http2]>=0.28.1
Requires-Dist: pydantic>=2.0
Requires-Dist: playwright>=1.5.0
Requires-Dist: aiohttp>=3.12.5
Requires-Dist: loguru>=0.7.0
Provides-Extra: test
Requires-Dist: pytest>=6.2.0; extra == "test"
Requires-Dist: pytest-cov>=2.12.0; extra == "test"
Requires-Dist: pytest-asyncio>=0.25.0; extra == "test"
Provides-Extra: dev
Requires-Dist: black>=21.0.0; extra == "dev"
Requires-Dist: flake8>=3.9.0; extra == "dev"
Requires-Dist: mypy>=0.910; extra == "dev"
Requires-Dist: isort>=5.10.0; extra == "dev"
Requires-Dist: playwright>=1.5.0; extra == "dev"
Requires-Dist: mcp>=1.0.0; extra == "dev"
Dynamic: license-file
